AppiumAndroid/__init__.py
AppiumAndroid/webdriver.py
AppiumAndroid-0.1.2.dist-info/METADATA
AppiumAndroid-0.1.2.dist-info/WHEEL
AppiumAndroid-0.1.2.dist-info/top_level.txt
AppiumAndroid-0.1.2.dist-info/RECORD
