Metadata-Version: 1.1
Name: AppiumAndroid
Version: 0.1.2
Summary: UNKNOWN
Home-page: UNKNOWN
Author: zhenghong
Author-email: 743872668@qq.com
License: UNKNOWN
Platform: UNKNOWN
Classifier: Programming Language :: Python :: 3
Classifier: License :: OSI Approved :: MIT License
Classifier: Operating System :: OS Independent
